{
  "尚未建立完成": "作成は未完了です",
  "訂單完成(尚未審核)": "注文完了（審査待ち）",
  "交易開始": "取引開始",
  "交易完成": "取引完了",
  "結算完成": "決済完了",
  "交易完成，扣捕點失敗": "取引完了、ポイント差引・補充失敗",
  "交易失敗": "取引失敗",
  "交易序號": "取引シリアル番号",
  "匯款銀行": "振込銀行",
  "匯款人": "振込人",
  "處理中": "処理中",
  "支付寶": "アリペイ",
  "真人百家樂": "ライブバカラ",
  "下注金額": "ベット金額",
  "有效投注": "有効なベット",
  "各項報表": "各種レポート",
  "存款紀錄": "預金履歴",
  "取款紀錄": "出金履歴",
  "遊戲紀錄": "ゲーム履歴",
  "起始日期": "開始日",
  "結束日期": "終了日",
  "搜尋": "検索",
  "本日": "本日",
  "前日": "前日",
  "本週": "今週",
  "注意事項": "注意事項",
  "每次提款最少點數為1000點以上，請務必確認填寫之帳號，若提供的帳號錯誤，恕本公司無法負責。": "毎回の出金最低ポイントは1000点以上とします。ご記入の口座番号を必ずご確認ください。ご提供いただいた口座番号が誤っていた場合、当社は一切責任を負いません。",
  "提款時需達到存款總金額的100%有效投注量才可提出申請。(PS:如利用本平臺進行任何洗錢詐騙行為，本公司保留權利審核會員帳戶或停權終止會員服務)": "お引き出し時は預金総額の100%有効なベット量に達さなければ申請することはできません（PS:当プラットフォームを利用して如何なるマネーロンダリング行為を行なった場合、当社は会員アカウントの審査または会員サービスを中止する権利を保留します）。",
  "期間總下注金額": "期間中の総ベット金額",
  "期間總有效投注": "期間中の総有効ベット",
  "期間總派彩": "期間中の総配当",
  "99電子": "99電子",
  "電子娛樂": "電子娯楽"
}