{
  "錯誤": "Lỗi",
  "請輸入您的暱稱": "Vui lòng nhập biệt hiệu của bạn",
  "成功": "Thành công",
  "暱稱修改完成": "Hoàn tất sửa đổi biệt hiệu",
  "網路異常, 請重新嘗試": "Mạng không bình thường, vui lòng thử lại",
  "請輸入錢包原始密碼": "Vui lòng nhập mật khẩu ban đầu của ví",
  "請輸入錢包新密碼": "Vui lòng nhập mật khẩu ví mới",
  "密碼須超過 8 位數": "Mật khẩu phải vượt quá 8 chữ số",
  "密碼不行超過 16 位數": "Mật khẩu không được vượt quá 16 chữ số",
  "請輸入英文或數字 8-16 位數": "Vui lòng nhập tiếng Anh hoặc số 8-16 chữ số",
  "驗證密碼失敗": "Xác minh mật khẩu thất bại",
  "錢包新密碼已設定完成": "Hoàn thành cài đặt mật khẩu mới của ví",
  "請輸入帳戶原始密碼": "Vui lòng nhập mật khẩu tài khoản ban đầu",
  "請輸入帳戶新密碼": "Vui lòng nhập mật khẩu mới cho tài khoản",
  "帳戶新密碼已設定完成": "Hoàn thành cài đặt mật khẩu mới của tài khoản",
  "修改": "Sửa đổi",
  "尚未設定": "Chưa cài đặt",
  "設定": "Cài đặt",
  "網路錯誤": "Lỗi mạng",
  "會員中心": "Trung tâm thành viên",
  "會員資料": "Hồ sơ thành viên",
  "代理資料": "Hồ sơ đại lý",
  "個人資料": "Hồ sơ cá nhân",
  "會員等級": "Cấp độ thành viên",
  "可用幣別": "Tiền tệ khả dụng",
  "真實姓名": "Tên thật",
  "暱稱": "Biệt hiệu",
  "修改暱稱": "Thay đổi biệt hiệu",
  "輸入新暱稱": "Nhập biệt hiệu mới",
  "取消": "Hủy bỏ",
  "確定修改": "Xác nhận sửa đổi",
  "電話": "Điện thoại",
  "我的推薦碼": "Mã giới thiệu của tôi",
  "顯示二維碼": "Hiển thị mã QR",
  "帳號資料": "Tư liệu tài khoản",
  "帳號": "Số tài khoản",
  "帳號密碼": "Mật khẩu tài khoản",
  "修改帳號密碼": "Thay đổi mật khẩu tài khoản",
  "輸入舊密碼": "Nhập mật khẩu cũ",
  "設定新密碼": "Đặt mật khẩu mới",
  "確認新密碼": "Xác nhận mật khẩu mới",
  "錢包密碼": "Mật khẩu ví",
  "修改錢包密碼": "Thay đổi mật khẩu ví",
  "帳號狀態": "Tình trạng tài khoản",
  "不可提款": "Không thể rút tiền",
  "提款所需投注": "Cược cần để rút tiền",
  "目前有效投注": "Cược hợp lệ hiện tại",
  "我的二維碼": "Mã QR của tôi",
  "關閉": "Tắt",
  "下載圖片": "Tải ảnh xuống"
}